setup.py
guassian_binomial_distributions/Binomialdistribution.py
guassian_binomial_distributions/Gaussiandistribution.py
guassian_binomial_distributions/Generaldistribution.py
guassian_binomial_distributions/__init__.py
guassian_binomial_distributions.egg-info/PKG-INFO
guassian_binomial_distributions.egg-info/SOURCES.txt
guassian_binomial_distributions.egg-info/dependency_links.txt
guassian_binomial_distributions.egg-info/not-zip-safe
guassian_binomial_distributions.egg-info/top_level.txt