Metadata-Version: 1.0
Name: guassian-binomial-distributions
Version: 1.0
Summary: Gaussian and Binomial distributions
Home-page: UNKNOWN
Author: MD Sabbir Hossain
Author-email: falaksabbir3@gmail.com
License: UNKNOWN
Platform: UNKNOWN
